wcl_services/__init__.py
wcl_services/analytic.py
wcl_services/customer.py
wcl_services/order.py
wcl_services/product.py
wcl_services/subscription.py
wcl_services/worker.py
wcl_services/tests/__init__.py
wcl_services-0.1.6.dist-info/DESCRIPTION.rst
wcl_services-0.1.6.dist-info/METADATA
wcl_services-0.1.6.dist-info/metadata.json
wcl_services-0.1.6.dist-info/RECORD
wcl_services-0.1.6.dist-info/top_level.txt
wcl_services-0.1.6.dist-info/WHEEL
