Metadata-Version: 2.0
Name: wcl-services
Version: 0.1.6
Summary: A client library for the Western Cape Labs HTTP Services APIs
Home-page: http://github.com/westerncapelabs/wcl-services
Author: Western Cape Labs
Author-email: devops@westerncapelabs.com
License: None
Platform: UNKNOWN
Classifier: Development Status :: 4 - Beta
Classifier: Intended Audience :: Developers
Classifier: License :: OSI Approved :: BSD License
Classifier: Operating System :: POSIX
Classifier: Programming Language :: Python
Classifier: Topic :: Software Development :: Libraries :: Python Modules
Classifier: Topic :: System :: Networking
Requires-Dist: demands
